tpdp/__info__.py
tpdp/__init__.py
tpdp/__version__.py
tpdp/pipeline.py
tpdp-0.1.0.dist-info/METADATA
tpdp-0.1.0.dist-info/WHEEL
tpdp-0.1.0.dist-info/licenses/LICENSE
tpdp-0.1.0.dist-info/RECORD
